FlaskSimpleAuth.py
flasksimpleauth-36.0.dist-info/licenses/LICENSE
flasksimpleauth-36.0.dist-info/METADATA
flasksimpleauth-36.0.dist-info/WHEEL
flasksimpleauth-36.0.dist-info/top_level.txt
flasksimpleauth-36.0.dist-info/RECORD
