Metadata-Version: 2.4
Name: FlaskSimpleAuth
Version: 36.0
Summary: Simple authentication, authorization and parameters for Flask, emphasizing configurability
Author-email: Fabien Coelho <flask.auth@coelho.net>
License-Expression: CC0-1.0
Project-URL: repository, https://github.com/zx80/flask-simple-auth
Project-URL: documentation, https://zx80.github.io/flask-simple-auth/
Project-URL: issues, https://github.com/zx80/flask-simple-auth/issues
Project-URL: package, https://pypi.org/project/FlaskSimpleAuth/
Classifier: Development Status :: 5 - Production/Stable
Classifier: Intended Audience :: Developers
Classifier: Programming Language :: Python
Classifier: Environment :: Web Environment
Classifier: Framework :: Flask
Classifier: Topic :: Software Development :: Libraries :: Python Modules
Requires-Python: >=3.10
License-File: LICENSE
Requires-Dist: flask>=3.0
Requires-Dist: ProxyPatternPool>=1.0
Requires-Dist: CacheToolsUtils>=10.0
Provides-Extra: dev
Requires-Dist: mypy; extra == "dev"
Requires-Dist: pyright; extra == "dev"
Requires-Dist: types-flask; extra == "dev"
Requires-Dist: types-requests; extra == "dev"
Requires-Dist: types-cachetools; extra == "dev"
Requires-Dist: types-redis; extra == "dev"
Requires-Dist: flake8; extra == "dev"
Requires-Dist: black; extra == "dev"
Requires-Dist: ruff; extra == "dev"
Requires-Dist: pytest; extra == "dev"
Requires-Dist: coverage; extra == "dev"
Requires-Dist: pymarkdownlnt!=0.9.5; extra == "dev"
Provides-Extra: pub
Requires-Dist: build; extra == "pub"
Requires-Dist: twine; extra == "pub"
Requires-Dist: wheel; extra == "pub"
Provides-Extra: doc
Requires-Dist: sphinx; extra == "doc"
Requires-Dist: sphinx_rtd_theme; extra == "doc"
Requires-Dist: sphinx-autoapi; extra == "doc"
Requires-Dist: sphinx-lint; extra == "doc"
Requires-Dist: myst_parser; extra == "doc"
Provides-Extra: tests
Requires-Dist: requests; extra == "tests"
Requires-Dist: pydantic>=2.0; extra == "tests"
Provides-Extra: demo
Requires-Dist: anodb; extra == "demo"
Requires-Dist: psycopg; extra == "demo"
Requires-Dist: psycopg2; extra == "demo"
Requires-Dist: types-cachetools; extra == "demo"
Provides-Extra: password
Requires-Dist: bcrypt; extra == "password"
Requires-Dist: argon2-cffi; extra == "password"
Requires-Dist: scrypt; extra == "password"
Requires-Dist: pyotp; extra == "password"
Requires-Dist: passlib; extra == "password"
Requires-Dist: crypt_r; python_version >= "3.13" and extra == "password"
Provides-Extra: ldap
Requires-Dist: ldap3; extra == "ldap"
Provides-Extra: redis
Requires-Dist: redis; extra == "redis"
Provides-Extra: memcached
Requires-Dist: pymemcache; extra == "memcached"
Provides-Extra: jwt
Requires-Dist: pyjwt; extra == "jwt"
Requires-Dist: cryptography; extra == "jwt"
Provides-Extra: cors
Requires-Dist: flask_cors; extra == "cors"
Provides-Extra: httpauth
Requires-Dist: flask_httpauth; extra == "httpauth"
Dynamic: license-file
